richconsole/__init__.py
richconsole/richconsole.py
richconsole-0.0.1.dist-info/LICENSE.txt
richconsole-0.0.1.dist-info/METADATA
richconsole-0.0.1.dist-info/WHEEL
richconsole-0.0.1.dist-info/top_level.txt
richconsole-0.0.1.dist-info/RECORD
