Metadata-Version: 2.1
Name: richconsole
Version: 0.0.1
Summary: modify and add color to the console
Home-page: https://github.com/mSquared-25/RichConsole
Author: mSquared-25
Author-email: mSquared5Squared@gmail.com
License: UNKNOWN
Platform: UNKNOWN
Classifier: Programming Language :: Python :: 2.7
Classifier: Programming Language :: Python :: 3
Classifier: License :: OSI Approved :: MIT License
Classifier: Operating System :: OS Independent
Requires-Python: >=2.7
